{
  "id": "did:web:recently-unique-lizard.ngrok-free.app",
  "verificationMethod": [
    {
      "type": "Bls12381G2Key2020",
      "id": "did:web:recently-unique-lizard.ngrok-free.app#keys-1",
      "controller": "did:web:recently-unique-lizard.ngrok-free.app",
      "publicKeyBase58": "23j4d66N8TJ86irm2fyLQ7Ki1iQNaks12i8vFdd1ZD73iNXkaLFq4S1U3153oB33hwsm7JwSQdkhgW7KxYDJMmU6JkeCorF9HWKs6nUyTLuhLSZvE82WMsVHUFC9Du5F64Kq"
    }
  ],
  "@context": [
    "https://www.w3.org/ns/did/v1",
    "https://w3id.org/security/suites/bls12381-2020/v1"
  ],
  "authentication": [
    "did:web:recently-unique-lizard.ngrok-free.app#keys-1"
  ],
  "assertionMethod": [
    "did:web:recently-unique-lizard.ngrok-free.app#keys-1"
  ],
  "capabilityInvocation": [
    "did:web:recently-unique-lizard.ngrok-free.app#keys-1"
  ],
  "capabilityDelegation": [
    "did:web:recently-unique-lizard.ngrok-free.app#keys-1"
  ]
}